photoscanner/__init__.py
photoscanner/main.py
photoscanner-0.2.4.dist-info/entry_points.txt
photoscanner-0.2.4.dist-info/WHEEL
photoscanner-0.2.4.dist-info/METADATA
photoscanner-0.2.4.dist-info/RECORD
