Metadata-Version: 2.1
Name: photoscanner
Version: 0.2.4
Summary: A simple tool to digitalize printed photos using a greenscreen and a DSLR.
Home-page: https://github.com/Flova/PhotoScanner
License: MIT
Author: Florian Vahl
Author-email: florian@flova.de
Requires-Python: >=3.8,<4.0
Classifier: License :: OSI Approved :: MIT License
Classifier: Programming Language :: Python :: 3
Classifier: Programming Language :: Python :: 3.8
Classifier: Programming Language :: Python :: 3.9
Requires-Dist: argparse (>=1.4.0,<2.0.0)
Requires-Dist: imutils (>=0.5.3,<0.6.0)
Requires-Dist: numpy (>=1.19.1,<2.0.0)
Requires-Dist: opencv-python (>=4.4.0,<5.0.0)
